mcp_git_commit_generator/__init__.py
mcp_git_commit_generator/__main__.py
mcp_git_commit_generator/server.py
mcp_git_commit_generator-2.2.0.dist-info/WHEEL
mcp_git_commit_generator-2.2.0.dist-info/entry_points.txt
mcp_git_commit_generator-2.2.0.dist-info/METADATA
mcp_git_commit_generator-2.2.0.dist-info/RECORD
