Metadata-Version: 2.3
Name: mcp-git-commit-generator
Version: 2.2.0
Summary: Generate conventional commit messages from your staged git changes using Model Context Protocol (MCP).
Keywords: mcp,model context protocol,git,commit,conventional commits,conventional commit messages
Author: Theoklitos Bampouris
Author-email: Theoklitos Bampouris <th.bampouris@gmail.com>
License: MIT
Classifier: Programming Language :: Python :: 3
Classifier: Operating System :: OS Independent
Requires-Dist: click>=8.2.1
Requires-Dist: mcp[cli]>=1.10.1
Maintainer: Theoklitos Bampouris
Maintainer-email: Theoklitos Bampouris <th.bampouris@gmail.com>
Requires-Python: >=3.14.0
Project-URL: Homepage, https://github.com/theoklitosBam7/mcp-git-commit-generator
Project-URL: Issues, https://github.com/theoklitosBam7/mcp-git-commit-generator/issues
